[ 
	{ 
		"enabled": true,
		"side": "Server", 
		"file": "game:itemtypes/tool/shield", 
		"op": "replace", 
		"path": "/class", 
		"value": "meleeweaponsframework:generic-shield"
	},
	{ 
		"enabled": true,
		"side": "Server", 
		"file": "game:itemtypes/tool/shield", 
		"op": "replace", 
		"path": "/attributes/shield", 
		"value": {
			"blockSound": "",
			"protectionChance": {
				"passive": 0,
				"active": 0
			},
			"damageAbsorption": {
				"passive": 0,
				"active": 0
			}
		}
	},
	{ 
		"enabled": true,
		"side": "Server", 
		"file": "game:itemtypes/tool/shield", 
		"op": "add", 
		"path": "/attributes/melee-weapon-stats", 
		"value": {
			"IdleAnimation": "idle1",
			"ReadyAnimation": "idle1",
			"BlockAnimation": "raiseshield-left",
			"BlockEaseInTimeMs": 200,
			"BlockEaseOutTimeMs": 200,
			"PerfectBlockWindowMs": 300,
			"CoverageDegrees": 120,
			"DamageMultiplierByType": {
				"*-crude": 0.4,
				"*-woodmetal": 0.6,
				"*-woodmetalleather": 0.70,
				"*-metal": 0.90,
				"*-blackguard": 0.90
			},
			"BlockSound": "game:sounds/held/shieldblock",
			"PerfectBlockSound": "game:sounds/block/ingot"
		}
	}
]